.gitignore
.travis.yml
AUTHORS
CHANGELOG
DEVELOPERS
LICENSE.txt
README.md
README.rst
mkdocs.sh
nosegae.py
runtests.sh
setup.cfg
setup.py
NoseGAE.egg-info/PKG-INFO
NoseGAE.egg-info/SOURCES.txt
NoseGAE.egg-info/dependency_links.txt
NoseGAE.egg-info/entry_points.txt
NoseGAE.egg-info/not-zip-safe
NoseGAE.egg-info/pbr.json
NoseGAE.egg-info/requires.txt
NoseGAE.egg-info/top_level.txt
docs/index.html
examples/install-gcloud-sdk.sh
examples/test_requirements.txt
examples/app_with_logging/app.yaml
examples/app_with_logging/main.py
examples/app_with_logging/runtests.sh
examples/app_with_logging/helloworld/__init__.py
examples/app_with_logging/tests/__init__.py
examples/app_with_logging/tests/test.py
examples/function_manual_config/app.yaml
examples/function_manual_config/helloworld.py
examples/function_manual_config/queue.yaml
examples/function_manual_config/runtests.sh
examples/function_manual_config/test.py
examples/helloworld/app.yaml
examples/helloworld/helloworld.py
examples/helloworld/runtests.sh
examples/helloworld/test.py
examples/issue-38-ndb-transactions/app.yaml
examples/issue-38-ndb-transactions/helloworld.py
examples/issue-38-ndb-transactions/runtests.sh
examples/issue-38-ndb-transactions/test.py
examples/issue02/app.yaml
examples/issue02/issue02.py
examples/issue02/runtests.sh
examples/issue02/test.py
examples/issue07/app.yaml
examples/issue07/main.py
examples/issue07/runtests.sh
examples/issue07/helloworld/__init__.py
examples/issue07/helloworld/models.py
examples/issue07/tests/__init__.py
examples/issue07/tests/test.py
examples/issue07/tests/test_models.py
examples/issue13-get_current_user/app.yaml
examples/issue13-get_current_user/helloworld.py
examples/issue13-get_current_user/runtests.sh
examples/issue13-get_current_user/test.py
examples/issue42_task-queue/app.yaml
examples/issue42_task-queue/helloworld.py
examples/issue42_task-queue/queue.yaml
examples/issue42_task-queue/runtests.sh
examples/issue42_task-queue/test.py
examples/modules_example/.gitignore
examples/modules_example/CONTRIB.md
examples/modules_example/LICENSE
examples/modules_example/README.md
examples/modules_example/app.yaml
examples/modules_example/dispatch.yaml
examples/modules_example/favicon.ico
